{
  "$schema": "https://ui.shadcn.com/schema/registry-item.json",
  "name": "spinner",
  "type": "registry:ui",
  "title": "Spinner",
  "description": "A spinner component",
  "registryDependencies": [
    "https://ui.ednesdayw.com/r/spinner-css.json"
  ],
  "files": [
    {
      "path": "src/registry/ui/spinner.tsx",
      "content": "import { cn } from \"@/lib/utils\";\nimport { VariantProps, cva } from \"class-variance-authority\";\n\nconst spinnerVariants = cva(\"[--sk-color:var(--primary)]\", {\n  variants: {\n    size: {\n      sm: \"[--sk-size:28px]\",\n      md: \"[--sk-size:34px]\",\n      lg: \"[--sk-size:40px]\",\n    },\n  },\n  defaultVariants: {\n    size: \"md\",\n  },\n});\n\nexport interface SpinnerProps\n  extends React.HTMLAttributes<HTMLDivElement>,\n    VariantProps<typeof spinnerVariants> {}\n\nexport const Spinner = ({\n  size,\n  className,\n  variant,\n  ...props\n}: SpinnerProps & {\n  variant:\n    | \"plane\"\n    | \"chase\"\n    | \"bounce\"\n    | \"wave\"\n    | \"pulse\"\n    | \"flow\"\n    | \"swing\"\n    | \"circle\"\n    | \"circle-fade\"\n    | \"grid\"\n    | \"fold\"\n    | \"wander\";\n}) => {\n  switch (variant) {\n    case \"plane\":\n      return <PlaneSpinner size={size} className={className} {...props} />;\n    case \"chase\":\n      return <ChaseSpinner size={size} className={className} {...props} />;\n    case \"bounce\":\n      return <BounceSpinner size={size} className={className} {...props} />;\n    case \"wave\":\n      return <WaveSpinner size={size} className={className} {...props} />;\n    case \"pulse\":\n      return <PulseSpinner size={size} className={className} {...props} />;\n    case \"flow\":\n      return <FlowSpinner size={size} className={className} {...props} />;\n    case \"swing\":\n      return <SwingSpinner size={size} className={className} {...props} />;\n    case \"circle\":\n      return <CircleSpinner size={size} className={className} {...props} />;\n    case \"circle-fade\":\n      return <CircleFadeSpinner size={size} className={className} {...props} />;\n    case \"grid\":\n      return <GridSpinner size={size} className={className} {...props} />;\n    case \"fold\":\n      return <FoldSpinner size={size} className={className} {...props} />;\n    case \"wander\":\n      return <WanderSpinner size={size} className={className} {...props} />;\n    default:\n      return <PlaneSpinner size={size} className={className} {...props} />;\n  }\n};\n\nexport const PlaneSpinner = ({ size, className, ...props }: SpinnerProps) => {\n  return (\n    <div\n      role=\"status\"\n      aria-label=\"Loading\"\n      className={cn(\"sk-plane\", spinnerVariants({ size }), className)}\n      {...props}\n    />\n  );\n};\n\nexport const ChaseSpinner = ({ size, className, ...props }: SpinnerProps) => {\n  return (\n    <div\n      role=\"status\"\n      aria-label=\"Loading\"\n      className={cn(\"sk-chase\", spinnerVariants({ size }), className)}\n      {...props}\n    >\n      <div className=\"sk-chase-dot\" />\n      <div className=\"sk-chase-dot\" />\n      <div className=\"sk-chase-dot\" />\n      <div className=\"sk-chase-dot\" />\n      <div className=\"sk-chase-dot\" />\n      <div className=\"sk-chase-dot\" />\n    </div>\n  );\n};\n\nexport const BounceSpinner = ({ size, className, ...props }: SpinnerProps) => {\n  return (\n    <div\n      role=\"status\"\n      aria-label=\"Loading\"\n      className={cn(\"sk-bounce\", spinnerVariants({ size }), className)}\n      {...props}\n    >\n      <div className=\"sk-bounce-dot\" />\n      <div className=\"sk-bounce-dot\" />\n    </div>\n  );\n};\n\nexport const WaveSpinner = ({ size, className, ...props }: SpinnerProps) => {\n  return (\n    <div\n      role=\"status\"\n      aria-label=\"Loading\"\n      className={cn(\"sk-wave\", spinnerVariants({ size }), className)}\n      {...props}\n    >\n      <div className=\"sk-wave-rect\" />\n      <div className=\"sk-wave-rect\" />\n      <div className=\"sk-wave-rect\" />\n      <div className=\"sk-wave-rect\" />\n    </div>\n  );\n};\n\nexport const PulseSpinner = ({ size, className, ...props }: SpinnerProps) => {\n  return (\n    <div\n      role=\"status\"\n      aria-label=\"Loading\"\n      className={cn(\"sk-pulse\", spinnerVariants({ size }), className)}\n      {...props}\n    />\n  );\n};\n\nexport const FlowSpinner = ({ size, className, ...props }: SpinnerProps) => {\n  return (\n    <div\n      role=\"status\"\n      aria-label=\"Loading\"\n      className={cn(\"sk-flow\", spinnerVariants({ size }), className)}\n      {...props}\n    >\n      <div className=\"sk-flow-dot\" />\n      <div className=\"sk-flow-dot\" />\n      <div className=\"sk-flow-dot\" />\n    </div>\n  );\n};\n\nexport const SwingSpinner = ({ size, className, ...props }: SpinnerProps) => {\n  return (\n    <div\n      role=\"status\"\n      aria-label=\"Loading\"\n      className={cn(\"sk-swing\", spinnerVariants({ size }), className)}\n      {...props}\n    >\n      <div className=\"sk-swing-dot\" />\n      <div className=\"sk-swing-dot\" />\n    </div>\n  );\n};\n\nexport const CircleSpinner = ({ size, className, ...props }: SpinnerProps) => {\n  return (\n    <div\n      role=\"status\"\n      aria-label=\"Loading\"\n      className={cn(\"sk-circle\", spinnerVariants({ size }), className)}\n      {...props}\n    >\n      <div className=\"sk-circle-dot\" />\n      <div className=\"sk-circle-dot\" />\n      <div className=\"sk-circle-dot\" />\n      <div className=\"sk-circle-dot\" />\n      <div className=\"sk-circle-dot\" />\n      <div className=\"sk-circle-dot\" />\n      <div className=\"sk-circle-dot\" />\n      <div className=\"sk-circle-dot\" />\n      <div className=\"sk-circle-dot\" />\n      <div className=\"sk-circle-dot\" />\n      <div className=\"sk-circle-dot\" />\n      <div className=\"sk-circle-dot\" />\n    </div>\n  );\n};\n\nexport const CircleFadeSpinner = ({\n  size,\n  className,\n  ...props\n}: SpinnerProps) => {\n  return (\n    <div\n      role=\"status\"\n      aria-label=\"Loading\"\n      className={cn(\"sk-circle-fade\", spinnerVariants({ size }), className)}\n      {...props}\n    >\n      <div className=\"sk-circle-fade-dot\" />\n      <div className=\"sk-circle-fade-dot\" />\n      <div className=\"sk-circle-fade-dot\" />\n      <div className=\"sk-circle-fade-dot\" />\n      <div className=\"sk-circle-fade-dot\" />\n      <div className=\"sk-circle-fade-dot\" />\n      <div className=\"sk-circle-fade-dot\" />\n      <div className=\"sk-circle-fade-dot\" />\n      <div className=\"sk-circle-fade-dot\" />\n      <div className=\"sk-circle-fade-dot\" />\n      <div className=\"sk-circle-fade-dot\" />\n      <div className=\"sk-circle-fade-dot\" />\n    </div>\n  );\n};\n\nexport const GridSpinner = ({ size, className, ...props }: SpinnerProps) => {\n  return (\n    <div\n      role=\"status\"\n      aria-label=\"Loading\"\n      className={cn(\"sk-grid\", spinnerVariants({ size }), className)}\n      {...props}\n    >\n      <div className=\"sk-grid-cube\" />\n      <div className=\"sk-grid-cube\" />\n      <div className=\"sk-grid-cube\" />\n      <div className=\"sk-grid-cube\" />\n      <div className=\"sk-grid-cube\" />\n      <div className=\"sk-grid-cube\" />\n      <div className=\"sk-grid-cube\" />\n      <div className=\"sk-grid-cube\" />\n      <div className=\"sk-grid-cube\" />\n    </div>\n  );\n};\n\nexport const FoldSpinner = ({ size, className, ...props }: SpinnerProps) => {\n  return (\n    <div\n      role=\"status\"\n      aria-label=\"Loading\"\n      className={cn(\"sk-fold\", spinnerVariants({ size }), className)}\n      {...props}\n    >\n      <div className=\"sk-fold-cube\" />\n      <div className=\"sk-fold-cube\" />\n      <div className=\"sk-fold-cube\" />\n      <div className=\"sk-fold-cube\" />\n    </div>\n  );\n};\n\nexport const WanderSpinner = ({ size, className, ...props }: SpinnerProps) => {\n  return (\n    <div\n      role=\"status\"\n      aria-label=\"Loading\"\n      className={cn(\"sk-wander\", spinnerVariants({ size }), className)}\n      {...props}\n    >\n      <div className=\"sk-wander-cube\" />\n      <div className=\"sk-wander-cube\" />\n    </div>\n  );\n};\n",
      "type": "registry:ui",
      "target": "components/wed/spinner.tsx"
    }
  ],
  "css": {
    "@import \"@/styles/spinkit.css\";": {}
  }
}